privscan/__init__.py
privscan/__main__.py
privscan/cli/__init__.py
privscan/cli/main.py
privscan/detectors/__init__.py
privscan/detectors/secrets.py
privscan/engine/__init__.py
privscan/engine/engine.py
privscan/engine/location.py
privscan/reporter/__init__.py
privscan/reporter/json_reporter.py
privscan/reporter/summary.py
privscan/reporter/table.py
privscan/rules/__init__.py
privscan/rules/loader.py
privscan/rules/models.py
privscan/scanner/__init__.py
privscan/scanner/filesystem.py
privscan/scanner/reader.py
privscan-0.1.0.dist-info/METADATA
privscan-0.1.0.dist-info/WHEEL
privscan-0.1.0.dist-info/entry_points.txt
privscan-0.1.0.dist-info/top_level.txt
privscan-0.1.0.dist-info/RECORD
